bay_adder.py
bay_adder-0.0.2.data/scripts/helloworld
bay_adder-0.0.2.dist-info/METADATA
bay_adder-0.0.2.dist-info/WHEEL
bay_adder-0.0.2.dist-info/top_level.txt
bay_adder-0.0.2.dist-info/RECORD
