Metadata-Version: 2.1
Name: bay-adder
Version: 0.0.2
Summary: Adds two nums
Home-page: UNKNOWN
Author: Alex Bers
Author-email: bay@hackerdom.ru
License: UNKNOWN
Platform: UNKNOWN
Classifier: Programming Language :: Python :: 3
Classifier: License :: OSI Approved :: MIT License
Classifier: Operating System :: OS Independent
